bocl/OCLWrapper.py
bocl/__init__.py
bocl/evaluator.py
models/__init__.py
models/library_object.py
models/researcher_object.py
models/team_player_object.py
bocl-0.3.1.dist-info/METADATA
bocl-0.3.1.dist-info/WHEEL
bocl-0.3.1.dist-info/top_level.txt
bocl-0.3.1.dist-info/RECORD
