Metadata-Version: 2.4
Name: bocl
Version: 0.3.1
Summary: B-OCL
Author: Luxembourg Institute of Science and Technology
License: MIT
Project-URL: Documentation, https://b-ocl-interpreter.readthedocs.io/en/latest/
Project-URL: Source Code, https://github.com/BESSER-PEARL/B-OCL-Interpreter
Project-URL: Bug Tracker, https://github.com/BESSER-PEARL/B-OCL-Interpreter/issues
Keywords: uml,code generation,python
Requires-Python: >=3.9
Requires-Dist: Arpeggio==2.0.2
Requires-Dist: colorama==0.4.6
Requires-Dist: iniconfig==2.0.0
Requires-Dist: packaging
Requires-Dist: pluggy==1.2.0
Requires-Dist: pytest==7.4.0
Requires-Dist: setuptools==68.2.2
Requires-Dist: textX==3.1.1
Requires-Dist: jinja2==3.1.2
Requires-Dist: antlr4-python3-runtime==4.13.1
Requires-Dist: requests==2.31.0
Requires-Dist: fastapi==0.110.0
Requires-Dist: pydantic==2.6.3
Requires-Dist: uvicorn==0.28.0
Requires-Dist: besser
